README.txt
setup.py
collective/__init__.py
collective.autorestart.egg-info/PKG-INFO
collective.autorestart.egg-info/SOURCES.txt
collective.autorestart.egg-info/dependency_links.txt
collective.autorestart.egg-info/entry_points.txt
collective.autorestart.egg-info/namespace_packages.txt
collective.autorestart.egg-info/not-zip-safe
collective.autorestart.egg-info/requires.txt
collective.autorestart.egg-info/top_level.txt
collective/autorestart/__init__.py
collective/autorestart/audio.py
collective/autorestart/bgthread.py
collective/autorestart/configure.zcml
collective/autorestart/logger.py
collective/autorestart/monitor.py
collective/autorestart/reload.pt
collective/autorestart/scanner.py
collective/autorestart/signalhandler.py
collective/autorestart/start.wav
collective/autorestart/youfail.wav
docs/HISTORY.txt