Metadata-Version: 1.0
Name: collective.autorestart
Version: 0.2.0
Summary: Automatically reloads changed code into Plone when you edit Python files
Home-page: http://pypi.python.org/pypi/collective.autorestart
Author: Mikko Ohtamaa
Author-email: mikko.ohtamaa@twinapex.com
License: GPL
Keywords: plone reload development server hotstart
Platform: UNKNOWN
Classifier: Programming Language :: Python
Classifier: Topic :: Software Development :: Libraries :: Python Modules
Classifier: Framework :: Plone
Classifier: Framework :: Zope2
